requireit.py
requireit-0.2.0.dist-info/licenses/LICENSE.md
requireit-0.2.0.dist-info/METADATA
requireit-0.2.0.dist-info/WHEEL
requireit-0.2.0.dist-info/top_level.txt
requireit-0.2.0.dist-info/RECORD
