Metadata-Version: 2.4
Name: requireit
Version: 0.2.0
Summary: Tiny runtime validators for explicit precondition checks
Author-email: Eric Hutton <mcflugen@gmail.com>
Maintainer-email: Eric Hutton <mcflugen@gmail.com>
License-Expression: MIT
Project-URL: homepage, https://github.com/mcflugen/requireit
Project-URL: documentation, https://github.com/mcflugen/requireit/blob/main/README.md
Project-URL: repository, https://github.com/mcflugen/requireit
Project-URL: changelog, https://github.com/mcflugen/requireit/blob/main/CHANGES.md
Keywords: preconditions,runtime-checks,utilities,validation
Classifier: Development Status :: 4 - Beta
Classifier: Intended Audience :: Developers
Classifier: Operating System :: OS Independent
Classifier: Programming Language :: Python :: 3
Classifier: Programming Language :: Python :: 3.10
Classifier: Programming Language :: Python :: 3.11
Classifier: Programming Language :: Python :: 3.12
Classifier: Programming Language :: Python :: 3.13
Classifier: Programming Language :: Python :: 3.14
Classifier: Programming Language :: Python :: 3 :: Only
Classifier: Programming Language :: Python :: Implementation :: CPython
Classifier: Programming Language :: Python :: Implementation :: PyPy
Requires-Python: >=3.10
License-File: LICENSE.md
Requires-Dist: numpy
Provides-Extra: dev
Requires-Dist: nox; extra == "dev"
Dynamic: license-file
